FYP_clustering/FYP_clustering.py
FYP_clustering/__init__.py
FYP_clustering-0.0.2.dist-info/METADATA
FYP_clustering-0.0.2.dist-info/WHEEL
FYP_clustering-0.0.2.dist-info/license.txt
FYP_clustering-0.0.2.dist-info/top_level.txt
FYP_clustering-0.0.2.dist-info/RECORD
